hashboard/__init__.py
hashboard/cli.py
hashboard/constants.py
hashboard/credentials.py
hashboard/filesystem.py
hashboard/session.py
hashboard/api/__init__.py
hashboard/api/access_keys/__init__.py
hashboard/api/access_keys/browser_auth.py
hashboard/api/access_keys/existing_user.py
hashboard/api/access_keys/utils.py
hashboard/api/analytics/__init__.py
hashboard/api/analytics/cli_with_tracking.py
hashboard/api/analytics/events.py
hashboard/api/build/__init__.py
hashboard/api/build/build_cli.py
hashboard/api/build/build_status_display.py
hashboard/api/build/dbt.py
hashboard/api/build/utils.py
hashboard/api/datasource/__init__.py
hashboard/api/datasource/datasource_cli.py
hashboard/api/datasource/utils.py
hashboard/dbt/__init__.py
hashboard/dbt/cloud_api.py
hashboard/dbt/dbt_properties.py
hashboard/utils/__init__.py
hashboard/utils/cli.py
hashboard/utils/config.py
hashboard/utils/display.py
hashboard/utils/env.py
hashboard/utils/grn.py
hashboard/utils/hbproject.py
hashboard/utils/input_validation.py
hashboard/utils/json_file.py
hashboard/utils/pull.py
hashboard/utils/resource.py
hashboard/utils/session_state.py
hashboard/utils/yaml_file.py
hashboard_cli-3.2.4.dist-info/licenses/LICENSE
hashboard_cli-3.2.4.dist-info/METADATA
hashboard_cli-3.2.4.dist-info/WHEEL
hashboard_cli-3.2.4.dist-info/entry_points.txt
hashboard_cli-3.2.4.dist-info/top_level.txt
hashboard_cli-3.2.4.dist-info/RECORD
